<?xml version="1.0" encoding="UTF-8"?>
<!--

    Copyright (C) 2013 Motown.IO (info@motown.io)

    Licensed under the Apache License, Version 2.0 (the "License");
    you may not use this file except in compliance with the License.
    You may obtain a copy of the License at

            http://www.apache.org/licenses/LICENSE-2.0

    Unless required by applicable law or agreed to in writing, software
    distributed under the License is distributed on an "AS IS" BASIS,
    WITHOUT WARRANTIES OR CONDITIONS OF ANY KIND, either express or implied.
    See the License for the specific language governing permissions and
    limitations under the License.

-->
<beans xmlns="http://www.springframework.org/schema/beans"
       xmlns:xsi="http://www.w3.org/2001/XMLSchema-instance"
       xmlns:context="http://www.springframework.org/schema/context"
       xsi:schemaLocation="http://www.springframework.org/schema/beans http://www.springframework.org/schema/beans/spring-beans-3.2.xsd
                           http://www.springframework.org/schema/context http://www.springframework.org/schema/context/spring-context-3.2.xsd">

    <context:property-placeholder location="classpath:config.properties"
                                  ignore-resource-not-found="true"/>

    <bean class="io.motown.identificationauthorization.app.AuthorizationEventListener">
        <property name="commandGateway" ref="authorizationCommandGateway" />
        <property name="identificationAuthorizationService" ref="identificationAuthorizationService" />
        <property name="addOnIdentity" value="1" />
    </bean>

    <bean id="identificationAuthorizationService" class="io.motown.identificationauthorization.app.IdentificationAuthorizationService">
        <property name="providers">
            <set>
                <!-- Using a dummy identification authentication for testing/demo's, this implementation will always return 'identification valid' -->
                <bean class="io.motown.sample.simple.authentication.DummyIdentificationAuthorization" />

                <!-- To enable CIR authentication, enable the lines below and enter a username/password and endpoint in the properties file. -->
                <!--
                <bean id="cirAuthentication" class="io.motown.identificationauthorization.cirplugin.CirAuthorization>
                    <property name="username" value="${io.motown.identificationauthorization.cirplugin.cirservice.username}" />
                    <property name="password" value="${io.motown.identificationauthorization.cirplugin.cirservice.password}" />
                    <property name="endpoint" value="${io.motown.identificationauthorization.cirplugin.cirservice.endpoint}" />
                </bean>
                -->
            </set>
        </property>
    </bean>

    <bean id="beanValidationInterceptor" class="org.axonframework.commandhandling.interceptors.BeanValidationInterceptor"/>

    <bean id="authorizationCommandGateway" class="org.axonframework.commandhandling.gateway.CommandGatewayFactoryBean">
        <property name="commandBus" ref="commandBus"/>
        <property name="gatewayInterface" value="io.motown.identificationauthorization.app.AuthorizationCommandGateway"/>
    </bean>

</beans>
